py2static/__main__.py
py2static/default.spec_txt
py2static/process.py
py2static/version.py
py2static/cli/main.py
tests/test_py2static.py
tests/test_version.py
py2static-0.0.1.dist-info/LICENSE
py2static-0.0.1.dist-info/METADATA
py2static-0.0.1.dist-info/WHEEL
py2static-0.0.1.dist-info/entry_points.txt
py2static-0.0.1.dist-info/top_level.txt
py2static-0.0.1.dist-info/RECORD
