Metadata-Version: 2.1
Name: py2static
Version: 0.0.1
Summary: Create static binaries from Python scripts
Home-page: https://github.com/joaompinto/py2static
Author: João Pinto
Author-email: lamego.pinto@gmail.com
License: MIT
License-File: LICENSE
Requires-Dist: pyinstaller
Requires-Dist: staticx
